adc_aios3/__init__.py
adc_aios3/client.py
adc_aios3-0.1.0.dist-info/METADATA
adc_aios3-0.1.0.dist-info/WHEEL
adc_aios3-0.1.0.dist-info/licenses/LICENSE
adc_aios3-0.1.0.dist-info/RECORD
