Metadata-Version: 2.4
Name: adc-aios3
Version: 0.1.0
Summary: Async S3 client with lifecycle management
Project-URL: Homepage, https://github.com/ascet-dev/adc-aios3
Project-URL: Documentation, https://adc-aios3.readthedocs.io/
Project-URL: Repository, https://github.com/ascet-dev/adc-aios3.git
Project-URL: Issues, https://github.com/ascet-dev/adc-aios3/issues
Author-email: Max <max@example.com>
License-Expression: MIT
License-File: LICENSE
Keywords: async,aws,s3,storage
Classifier: Development Status :: 4 - Beta
Classifier: Intended Audience :: Developers
Classifier: License :: OSI Approved :: MIT License
Classifier: Programming Language :: Python :: 3
Classifier: Programming Language :: Python :: 3.8
Classifier: Programming Language :: Python :: 3.9
Classifier: Programming Language :: Python :: 3.10
Classifier: Programming Language :: Python :: 3.11
Requires-Python: >=3.8
Requires-Dist: aiobotocore>=2.5.0
Requires-Dist: botocore>=1.29.0
